HISTORY.rst
MANIFEST.in
README.md
setup.py
LightNER.egg-info/PKG-INFO
LightNER.egg-info/SOURCES.txt
LightNER.egg-info/dependency_links.txt
LightNER.egg-info/entry_points.txt
LightNER.egg-info/not-zip-safe
LightNER.egg-info/requires.txt
LightNER.egg-info/top_level.txt
lightner/__init__.py
lightner/__main__.py
lightner/utils.py
lightner/basic_modules/__init__.py
lightner/basic_modules/basic_rnn.py
lightner/basic_modules/highway.py
lightner/basic_modules/ld_rnn.py
lightner/basic_modules/rnn.py
lightner/commands/__init__.py
lightner/commands/decoder.py
lightner/commands/main.py
lightner/crf_model/__init__.py
lightner/crf_model/crf.py
lightner/crf_model/denselm.py
lightner/crf_model/predictor.py
lightner/crf_model/seqlabel.py
lightner/two_level_model/__init__.py
lightner/two_level_model/autoner.py
lightner/two_level_model/predictor.py