Metadata-Version: 1.1
Name: LightNER
Version: 0.2.2
Summary: A Toolkit for Pre-trained Sequence Labeling Models Inference
Home-page: https://github.com/LiyuanLucasLiu/LightNER
Author: Lucas Liu
Author-email: llychinalz@gmail.com
License: Apache License 2.0
Platform: UNKNOWN
Classifier: Development Status :: 2 - Pre-Alpha
Classifier: Intended Audience :: Developers
Classifier: Natural Language :: English
Classifier: Programming Language :: Python :: 3
Classifier: Programming Language :: Python :: 3.4
Classifier: Programming Language :: Python :: 3.5
Classifier: Programming Language :: Python :: 3.6
